MANIFEST.in
README.md
openke_
setup.py
benchmarks/FB13/n-n.py
benchmarks/FB15K/n-n.py
benchmarks/FB15K237/n-n.py
benchmarks/WN11/n-n.py
benchmarks/WN18/n-n.py
benchmarks/WN18RR/n-n.py
openke/__init__.py
openke/__main__.py
openke/api.py
openke/example_test_transe.py
openke/example_train_transe.py
openke/make.sh
openke.egg-info/PKG-INFO
openke.egg-info/SOURCES.txt
openke.egg-info/dependency_links.txt
openke.egg-info/top_level.txt
openke/config/Config.py
openke/config/__init__.py
openke/data/PersistedDatasetAdapter.py
openke/data/RuntimeDatasetAdapter.py
openke/data/__init__.py
openke/data/utils.py
openke/examples/train_complex_FB15K237.py
openke/examples/train_complex_WN18.py
openke/examples/train_distmult_FB15K237.py
openke/examples/train_distmult_WN18.py
openke/examples/train_hole.py
openke/examples/train_rescal.py
openke/examples/train_transd_FB15K237.py
openke/examples/train_transd_WN18RR.py
openke/examples/train_transe_FB15K237.py
openke/examples/train_transe_WN18RR.py
openke/examples/train_transh_FB15K237.py
openke/examples/train_transh_WN18RR.py
openke/examples/train_transr_FB15K237.py
openke/examples/train_transr_WN18RR.py
openke/models/Analogy.py
openke/models/ComplEx.py
openke/models/DistMult.py
openke/models/HolE.py
openke/models/Model.py
openke/models/RESCAL.py
openke/models/TransD.py
openke/models/TransE.py
openke/models/TransH.py
openke/models/TransR.py
openke/models/__init__.py
openke/models/models/Analogy.py
openke/models/models/ComplEx.py
openke/models/models/DistMult.py
openke/models/models/HolE.py
openke/models/models/Model.py
openke/models/models/RESCAL.py
openke/models/models/TransD.py
openke/models/models/TransE.py
openke/models/models/TransH.py
openke/models/models/TransR.py
openke/models/models/__init__.py
openke/utils/__init__.py