Metadata-Version: 2.1
Name: openke
Version: 0.96
Summary: A library for operating knowledge graph models
Home-page: https://github.com/zeionara/OpenKE
Author-email: zeionara@gmail.com
License: UNKNOWN
Platform: UNKNOWN
Classifier: Programming Language :: Python :: 3
Classifier: License :: OSI Approved :: MIT License
Classifier: Operating System :: OS Independent
